shabbat/Shabbat.py
shabbat/__init__.py
shabbat-0.1.0.dist-info/METADATA
shabbat-0.1.0.dist-info/WHEEL
shabbat-0.1.0.dist-info/top_level.txt
shabbat-0.1.0.dist-info/RECORD
