Metadata-Version: 2.1
Name: shabbat
Version: 0.1.0
Summary: Identify whether the current date and time is Saturday or not.
Home-page: UNKNOWN
Author: moshe cohen
Author-email: moshe.cohen99435@gmail.com
License: MIT
Platform: UNKNOWN
Classifier: Intended Audience :: Developers
Classifier: License :: OSI Approved :: MIT License
Classifier: Programming Language :: Python
Classifier: Programming Language :: Python :: 3
Classifier: Programming Language :: Python :: 3.6
Classifier: Programming Language :: Python :: 3.7
Classifier: Programming Language :: Python :: 3.8
Classifier: Programming Language :: Python :: 3.9
Classifier: Operating System :: OS Independent
Requires-Dist: httpx
